beku/__init__.py
beku/__main__.py
beku/kuttl.py
beku/main.py
beku/version.py
beku/test/__init__.py
beku/test/test_render_from_stream.py
beku_stackabletech-0.0.10.dist-info/LICENSE
beku_stackabletech-0.0.10.dist-info/METADATA
beku_stackabletech-0.0.10.dist-info/WHEEL
beku_stackabletech-0.0.10.dist-info/entry_points.txt
beku_stackabletech-0.0.10.dist-info/top_level.txt
beku_stackabletech-0.0.10.dist-info/RECORD
