Metadata-Version: 2.1
Name: beku-stackabletech
Version: 0.0.10
Summary: Test suite expander for Stackable Kuttl tests.
Author-email: Razvan Mihai <razvan.mihai@stackable.tech>
Project-URL: Homepage, https://github.com/stackabletech/beku.py
Project-URL: Bug Tracker, https://github.com/stackabletech/beku.py/issues
Classifier: Programming Language :: Python :: 3
Classifier: License :: OSI Approved :: MIT License
Classifier: Operating System :: OS Independent
Requires-Python: >=3.7
License-File: LICENSE
Requires-Dist: Jinja2 >=3.1.2
Requires-Dist: PyYAML >=6.0
Provides-Extra: lint
Requires-Dist: ruff >=0.4 ; extra == 'lint'
Requires-Dist: mypy >=1.10 ; extra == 'lint'
Provides-Extra: publish
Requires-Dist: twine >=5.0 ; extra == 'publish'
Requires-Dist: build >=1.2 ; extra == 'publish'
